jax_plugins/intel_extension_for_openxla/__init__.py
jax_plugins/intel_extension_for_openxla/gen_xla_version.py
jax_plugins/intel_extension_for_openxla/pjrt_plugin_xpu.so
jax_plugins/intel_extension_for_openxla/version.py
jax_plugins/intel_extension_for_openxla/python/xpu_plugin_extension.so
jax_plugins/intel_extension_for_openxla/service/gpu/sycl_onednn.so
jax_plugins/intel_extension_for_openxla/third-party-programs/third-party-programs-of-onednn.txt
intel_extension_for_openxla-0.6.0.dist-info/METADATA
intel_extension_for_openxla-0.6.0.dist-info/WHEEL
intel_extension_for_openxla-0.6.0.dist-info/top_level.txt
intel_extension_for_openxla-0.6.0.dist-info/RECORD
