Metadata-Version: 2.2
Name: intel_extension_for_openxla
Version: 0.6.0
Summary: Intel® Extension for OpenXLA* library
Home-page: https://github.com/intel/intel-extension-for-openxla
Download-URL: https://github.com/intel/intel-extension-for-openxla/tags
Author: Intel Corporation
Author-email: itex.maintainers@intel.com
License: Apache 2.0
Project-URL: Bug Tracker, https://github.com/intel/intel-extension-for-openxla/issues
Keywords: Intel® Extension for OpenXLA*
Classifier: Development Status :: 5 - Production/Stable
Classifier: Intended Audience :: Developers
Classifier: Intended Audience :: Education
Classifier: Intended Audience :: Science/Research
Classifier: License :: OSI Approved :: Apache Software License
Classifier: Programming Language :: Python :: 3.9
Classifier: Programming Language :: Python :: 3.10
Classifier: Programming Language :: Python :: 3.11
Classifier: Programming Language :: Python :: 3.12
Classifier: Programming Language :: Python :: 3.13
Classifier: Topic :: Scientific/Engineering
Classifier: Topic :: Scientific/Engineering :: Mathematics
Classifier: Topic :: Scientific/Engineering :: Artificial Intelligence
Classifier: Topic :: Software Development
Classifier: Topic :: Software Development :: Libraries
Classifier: Topic :: Software Development :: Libraries :: Python Modules
Requires-Python: >=3.9
Requires-Dist: wheel
Requires-Dist: numpy>=1.24.0
Requires-Dist: scipy<1.12.0; python_version <= "3.12"
Requires-Dist: scipy<1.15.0; python_version == "3.13"
Dynamic: author
Dynamic: author-email
Dynamic: classifier
Dynamic: description
Dynamic: description-content-type
Dynamic: download-url
Dynamic: home-page
Dynamic: keywords
Dynamic: license
Dynamic: project-url
Dynamic: requires-dist
Dynamic: requires-python
Dynamic: summary
